{"graph": {"directed": true, "nodes": {"node_ab48f077": {"uid": "node_ab48f077", "label": "26: generate_model_from_fields()", "name": "_types::generate_model_from_fields"}, "node_f20e93df": {"uid": "node_f20e93df", "label": "26: get_html_template()", "name": "assets::get_html_template"}, "node_c182cdf0": {"uid": "node_c182cdf0", "label": "16: create_forecasting_agent_and_get_forecast()", "name": "forecaster::create_forecasting_agent_and_get_forecast"}, "node_b9a0ba4e": {"uid": "node_b9a0ba4e", "label": "65: save_prediction_analysis_html()", "name": "io::save_prediction_analysis_html"}, "node_8d5a8665": {"uid": "node_8d5a8665", "label": "13: create_prediction_agent_and_get_predictions()", "name": "predictor::create_prediction_agent_and_get_predictions"}}, "edges": [{"source": "node_c182cdf0", "target": "node_ab48f077", "directed": true}, {"source": "node_b9a0ba4e", "target": "node_f20e93df", "directed": true}, {"source": "node_8d5a8665", "target": "node_ab48f077", "directed": true}]}}