{"graph": {"directed": true, "nodes": {"node_c335c7c4": {"uid": "node_c335c7c4", "label": "11: calculate_expression()", "name": "server::calculate_expression"}, "node_0827399e": {"uid": "node_0827399e", "label": "167: format_result()", "name": "server::format_result"}, "node_57ab1cf7": {"uid": "node_57ab1cf7", "label": "66: handle_complex_integration()", "name": "server::handle_complex_integration"}, "node_256bef62": {"uid": "node_256bef62", "label": "133: handle_equation_solving()", "name": "server::handle_equation_solving"}, "node_1e2605e7": {"uid": "node_1e2605e7", "label": "145: handle_matrix_eigenvalues()", "name": "server::handle_matrix_eigenvalues"}, "node_6e3beac0": {"uid": "node_6e3beac0", "label": "14: test_algebraic_operations()", "name": "test_server::TestCalculateExpression.test_algebraic_operations"}, "node_82ac637b": {"uid": "node_82ac637b", "label": "8: test_basic_operations()", "name": "test_server::TestCalculateExpression.test_basic_operations"}, "node_9f4a0d8e": {"uid": "node_9f4a0d8e", "label": "20: test_calculus()", "name": "test_server::TestCalculateExpression.test_calculus"}, "node_6158a890": {"uid": "node_6158a890", "label": "26: test_equation_solving()", "name": "test_server::TestCalculateExpression.test_equation_solving"}, "node_dc54e41f": {"uid": "node_dc54e41f", "label": "37: test_error_handling()", "name": "test_server::TestCalculateExpression.test_error_handling"}, "node_b9945d1a": {"uid": "node_b9945d1a", "label": "31: test_matrix_operations()", "name": "test_server::TestCalculateExpression.test_matrix_operations"}}, "edges": [{"source": "node_c335c7c4", "target": "node_0827399e", "directed": true}, {"source": "node_c335c7c4", "target": "node_57ab1cf7", "directed": true}, {"source": "node_c335c7c4", "target": "node_256bef62", "directed": true}, {"source": "node_c335c7c4", "target": "node_1e2605e7", "directed": true}, {"source": "node_57ab1cf7", "target": "node_0827399e", "directed": true}, {"source": "node_256bef62", "target": "node_0827399e", "directed": true}, {"source": "node_1e2605e7", "target": "node_0827399e", "directed": true}, {"source": "node_6e3beac0", "target": "node_c335c7c4", "directed": true}, {"source": "node_6e3beac0", "target": "node_c335c7c4", "directed": true}, {"source": "node_6e3beac0", "target": "node_c335c7c4", "directed": true}, {"source": "node_82ac637b", "target": "node_c335c7c4", "directed": true}, {"source": "node_82ac637b", "target": "node_c335c7c4", "directed": true}, {"source": "node_82ac637b", "target": "node_c335c7c4", "directed": true}, {"source": "node_9f4a0d8e", "target": "node_c335c7c4", "directed": true}, {"source": "node_9f4a0d8e", "target": "node_c335c7c4", "directed": true}, {"source": "node_9f4a0d8e", "target": "node_c335c7c4", "directed": true}, {"source": "node_6158a890", "target": "node_c335c7c4", "directed": true}, {"source": "node_6158a890", "target": "node_c335c7c4", "directed": true}, {"source": "node_dc54e41f", "target": "node_c335c7c4", "directed": true}, {"source": "node_dc54e41f", "target": "node_c335c7c4", "directed": true}, {"source": "node_b9945d1a", "target": "node_c335c7c4", "directed": true}, {"source": "node_b9945d1a", "target": "node_c335c7c4", "directed": true}]}}